[
  {
    "id": "kinopoisk_pref_max_posters",
    "label": "Максимум обложек",
    "type": "enum",
    "values": ["0", "1", "2", "4", "6", "8", "10", "12", "14", "20"],
    "default": "1"
  },
  {
    "id": "kinopoisk_pref_max_art",
    "label": "Максимум фотографий",
    "type": "enum",
    "values": ["0", "2", "4", "6", "8", "10", "12", "14", "20", "40"],
    "default": "2"
  },
  {
	  "id": "kinopoisk_pref_get_all_actors",
		"label": "Брать всех актеров",
		"type": "bool",
		"default":	"false"
	},
  {
	  "id": "kinopoisk_pref_imdb_support",
		"label": "Поддержка IMDB",
		"type": "bool",
		"default":	"true"
	},
  {
    "id": "kinopoisk_pref_cache_time",
    "label": "Кэширование веб-данных",
    "type": "enum",
    "values": ["1 день", "1 неделя", "1 месяц", "1 год"],
    "default": "1 месяц"
  }
]